MANIFEST.in
setup.cfg
setup.py
docs/news.txt
stompclient/__init__.py
stompclient/connection.py
stompclient/duplex.py
stompclient/exceptions.py
stompclient/frame.py
stompclient/simplex.py
stompclient/util.py
stompclient.egg-info/PKG-INFO
stompclient.egg-info/SOURCES.txt
stompclient.egg-info/dependency_links.txt
stompclient.egg-info/top_level.txt