Metadata-Version: 1.0
Name: stompclient
Version: 0.3.2
Summary: 
